{
  "url": "https://sammlung.belvedere.at/internal/media/dispatcher/65368/preview",
  "title": "\"Charakterkopf\" Nr. 6",
  "description": "Durch die zusammengezogenen und nach vorn gedr\u00fcckten Muskeln und Knochen verzerrt sich die untere Gesichtspartie dieses Kopfes in die Form eines Schnabels und bleibt doch in der menschlichen Gestalt verhaftet. Messerschmidts \u201eCharakterk\u00f6pfe\u201c z\u00e4hlen zu den faszinierendsten Werken in der Sammlung des Belvedere. Die teils skurril anmutenden, teils irritierenden B\u00fcsten aus Alabaster oder Metall geben uns bis heute viele R\u00e4tsel auf. Der K\u00fcnstler selbst nannte die sonderbaren Artefakte schlicht \u201eKopfst\u00fccke\u201c. Erst nach seinem Tod wurden sie mit interpretierenden Titeln versehen. Immer wieder ist die unvergleichliche Werkgruppe ein beliebter Bezugspunkt f\u00fcr zeitgen\u00f6ssische k\u00fcnstlerische Auseinandersetzungen.",
  "description_page": "https://sammlung.belvedere.at/objects/4389/charakterkopf-nr-6?ctx=acf1875ac9c66ac2670fee0930f26ef36f123252&idx=46",
  "artist": "Franz Xaver Messerschmidt"
}