{
  "url": "https://sammlung.belvedere.at/internal/media/dispatcher/5358/preview",
  "title": "Stillleben mit Apfelkorb",
  "description": "Es sind allt\u00e4gliche, pr\u00e4zis wiedergegebene Gegenst\u00e4nde, die die Hauptrollen in den drei Darstellungen von Anna Maria Punz spielen. In ihrem n\u00fcchternen Arrangement stehen sie im Gegensatz zu den opulenten Prunkstillleben des Barock. Was hier modern anmutet und an die Neue Sachlichkeit der 1920er- und 1930er-Jahre denken l\u00e4sst, hat seine Wurzeln in der niederl\u00e4ndischen Stillebenmalerei der ersten H\u00e4lfte des 17. Jahrhunderts. Woher genau die Malerin die Inspiration f\u00fcr diese Gem\u00e4lde bezogen hat, ist nicht \u00fcberliefert. Wenn auch die groben Eckdaten ihres Lebens dokumentiert sind, l\u00e4sst sich ihr k\u00fcnstlerischer Werdegang bislang nicht nachvollziehen.",
  "description_page": "https://sammlung.belvedere.at/objects/5644/stillleben-mit-apfelkorb?ctx=fd4f3d33b1c3b301e901b446f27bdb8b57cc03d9&idx=313",
  "artist": "Anna Maria Punz"
}